setup.py
scikits/__init__.py
scikits.vectorplot.egg-info/PKG-INFO
scikits.vectorplot.egg-info/SOURCES.txt
scikits.vectorplot.egg-info/dependency_links.txt
scikits.vectorplot.egg-info/namespace_packages.txt
scikits.vectorplot.egg-info/requires.txt
scikits.vectorplot.egg-info/top_level.txt
scikits.vectorplot.egg-info/zip-safe
scikits/vectorplot/INSTALL.txt
scikits/vectorplot/README.txt
scikits/vectorplot/__init__.py
scikits/vectorplot/kernels.py
scikits/vectorplot/lic.py
scikits/vectorplot/lic_internal.c
scikits/vectorplot/lic_internal.pyx
scikits/vectorplot/setup.py
scikits/vectorplot/doc/lic_demo.py
scikits/vectorplot/doc/lic_efield_demo.py