Metadata-Version: 1.0
Name: scikits.vectorplot
Version: 0.1
Summary: Vector fields plotting algorithms.
Home-page: http://projects.scipy.org/scipy/scikits
Author: Anne Archibald
Author-email: peridot.faceted@gmail.com
License: BSD
Download-URL: http://projects.scipy.org/scipy/scikits
Platform: UNKNOWN
Classifier: Development Status :: 1 - Planning
Classifier: Environment :: Console
Classifier: Intended Audience :: Developers
Classifier: Intended Audience :: Science/Research
Classifier: License :: OSI Approved :: BSD License
Classifier: Topic :: Scientific/Engineering
